{"i":{"Identity":{"":null},"46f17e86cf1a0604f31c5b64f7ff1033":{"resource":{"i":{"it":{"46f17e86cf1a0604f31c5b64f7ff1033":{"repo":"https:\/\/sourceforge.net\/p\/chronolabsapis\/Fonting\/HEAD\/tree\/%s?format=raw","file":"ITC+Souvenir+Std+Medium.zip","path":"\/fonts\/Unpacking\/thatcher0:7d3b2bd7741d7f680e0438","files":[],"resource":{"it":{"i":{"it":{"46f17e86cf1a0604f31c5b64f7ff1033":{"repo":"https:\/\/sourceforge.net\/p\/chronolabsapis\/Fonting\/HEAD\/tree\/%s?format=raw","file":"ITC+Souvenir+Std+Medium.zip","path":"\/fonts\/Unpacking\/thatcher0:7d3b2bd7741d7f680e0438","files":[]}}}},"i":{"i":{"it":{"46f17e86cf1a0604f31c5b64f7ff1033":{"repo":"https:\/\/sourceforge.net\/p\/chronolabsapis\/Fonting\/HEAD\/tree\/%s?format=raw","file":"ITC+Souvenir+Std+Medium.zip","path":"\/fonts\/Unpacking\/thatcher0:7d3b2bd7741d7f680e0438","files":[],"resource":{"it":{"i":{"it":{"46f17e86cf1a0604f31c5b64f7ff1033":{"repo":"https:\/\/sourceforge.net\/p\/chronolabsapis\/Fonting\/HEAD\/tree\/%s?format=raw","file":"ITC+Souvenir+Std+Medium.zip","path":"\/fonts\/Unpacking\/thatcher0:7d3b2bd7741d7f680e0438","files":[]}}}}}}}}}}}}}}}}}