{"c":{"Identity":{"":null},"dac0aa88a1590347e0fd180d75ffcc2f":{"resource":{"c":{"ca":{"dac0aa88a1590347e0fd180d75ffcc2f":{"repo":"https:\/\/sourceforge.net\/p\/chronolabsapis\/Fonting\/HEAD\/tree\/%s?format=raw","file":"Cantoria+MT+Std+Light.zip","path":"\/fonts\/Unpacking\/f53d7b7ebf145c6a72dadc7432c4ec36","files":[],"resource":{"ca":{"c":{"ca":{"dac0aa88a1590347e0fd180d75ffcc2f":{"repo":"https:\/\/sourceforge.net\/p\/chronolabsapis\/Fonting\/HEAD\/tree\/%s?format=raw","file":"Cantoria+MT+Std+Light.zip","path":"\/fonts\/Unpacking\/f53d7b7ebf145c6a72dadc7432c4ec36","files":[]}}}},"c":{"c":{"ca":{"dac0aa88a1590347e0fd180d75ffcc2f":{"repo":"https:\/\/sourceforge.net\/p\/chronolabsapis\/Fonting\/HEAD\/tree\/%s?format=raw","file":"Cantoria+MT+Std+Light.zip","path":"\/fonts\/Unpacking\/f53d7b7ebf145c6a72dadc7432c4ec36","files":[],"resource":{"ca":{"c":{"ca":{"dac0aa88a1590347e0fd180d75ffcc2f":{"repo":"https:\/\/sourceforge.net\/p\/chronolabsapis\/Fonting\/HEAD\/tree\/%s?format=raw","file":"Cantoria+MT+Std+Light.zip","path":"\/fonts\/Unpacking\/f53d7b7ebf145c6a72dadc7432c4ec36","files":[]}}}}}}}}}}}}}}}}}