{"e":{"Identity":{"":null},"157a65d213b60d645604c59dcfa93344":{"resource":{"e":{"eg":{"157a65d213b60d645604c59dcfa93344":{"repo":"https:\/\/sourceforge.net\/p\/chronolabsapis\/Fonting\/HEAD\/tree\/%s?format=raw","file":"Egyptian+7+1+0.zip","path":"\/fonts\/Unpacking\/96832a78098c5244be3708fb8a654870","files":[],"resource":{"eg":{"e":{"eg":{"157a65d213b60d645604c59dcfa93344":{"repo":"https:\/\/sourceforge.net\/p\/chronolabsapis\/Fonting\/HEAD\/tree\/%s?format=raw","file":"Egyptian+7+1+0.zip","path":"\/fonts\/Unpacking\/96832a78098c5244be3708fb8a654870","files":[]}}}},"e":{"e":{"eg":{"157a65d213b60d645604c59dcfa93344":{"repo":"https:\/\/sourceforge.net\/p\/chronolabsapis\/Fonting\/HEAD\/tree\/%s?format=raw","file":"Egyptian+7+1+0.zip","path":"\/fonts\/Unpacking\/96832a78098c5244be3708fb8a654870","files":[],"resource":{"eg":{"e":{"eg":{"157a65d213b60d645604c59dcfa93344":{"repo":"https:\/\/sourceforge.net\/p\/chronolabsapis\/Fonting\/HEAD\/tree\/%s?format=raw","file":"Egyptian+7+1+0.zip","path":"\/fonts\/Unpacking\/96832a78098c5244be3708fb8a654870","files":[]}}}}}}}}}}}}}}}}}