{"s":{"Identity":{"":null},"c1deca4b98515b3645a88748b9eb429c":{"resource":{"s":{"sa":{"c1deca4b98515b3645a88748b9eb429c":{"repo":"https:\/\/sourceforge.net\/p\/chronolabsapis\/Fonting\/HEAD\/tree\/%s?format=raw","file":"Savannah+Fat.zip","path":"\/fonts\/Unpacking\/041cfd89bc183b716e080bbfe59c9abe","files":[],"resource":{"sa":{"s":{"sa":{"c1deca4b98515b3645a88748b9eb429c":{"repo":"https:\/\/sourceforge.net\/p\/chronolabsapis\/Fonting\/HEAD\/tree\/%s?format=raw","file":"Savannah+Fat.zip","path":"\/fonts\/Unpacking\/041cfd89bc183b716e080bbfe59c9abe","files":[]}}}},"s":{"s":{"sa":{"c1deca4b98515b3645a88748b9eb429c":{"repo":"https:\/\/sourceforge.net\/p\/chronolabsapis\/Fonting\/HEAD\/tree\/%s?format=raw","file":"Savannah+Fat.zip","path":"\/fonts\/Unpacking\/041cfd89bc183b716e080bbfe59c9abe","files":[],"resource":{"sa":{"s":{"sa":{"c1deca4b98515b3645a88748b9eb429c":{"repo":"https:\/\/sourceforge.net\/p\/chronolabsapis\/Fonting\/HEAD\/tree\/%s?format=raw","file":"Savannah+Fat.zip","path":"\/fonts\/Unpacking\/041cfd89bc183b716e080bbfe59c9abe","files":[]}}}}}}}}}}}}}}}}}