{"n":{"Identity":{"":null},"a51014080cb28718b024ebab920eff52":{"resource":{"n":{"ne":{"a51014080cb28718b024ebab920eff52":{"repo":"https:\/\/sourceforge.net\/p\/chronolabsapis\/Fonting\/HEAD\/tree\/%s?format=raw","file":"Nesobrite+Ex+Bl+Regular.zip","path":"\/fonts\/Unpacking\/aph:8936c6b41901cea2cfd90c59996f","files":[],"resource":{"ne":{"n":{"ne":{"a51014080cb28718b024ebab920eff52":{"repo":"https:\/\/sourceforge.net\/p\/chronolabsapis\/Fonting\/HEAD\/tree\/%s?format=raw","file":"Nesobrite+Ex+Bl+Regular.zip","path":"\/fonts\/Unpacking\/aph:8936c6b41901cea2cfd90c59996f","files":[]}}}},"n":{"n":{"ne":{"a51014080cb28718b024ebab920eff52":{"repo":"https:\/\/sourceforge.net\/p\/chronolabsapis\/Fonting\/HEAD\/tree\/%s?format=raw","file":"Nesobrite+Ex+Bl+Regular.zip","path":"\/fonts\/Unpacking\/aph:8936c6b41901cea2cfd90c59996f","files":[],"resource":{"ne":{"n":{"ne":{"a51014080cb28718b024ebab920eff52":{"repo":"https:\/\/sourceforge.net\/p\/chronolabsapis\/Fonting\/HEAD\/tree\/%s?format=raw","file":"Nesobrite+Ex+Bl+Regular.zip","path":"\/fonts\/Unpacking\/aph:8936c6b41901cea2cfd90c59996f","files":[]}}}}}}}}}}}}}}}}}